CHANGES.txt
MANIFEST.in
README.txt
setup.cfg
setup.py
ZenPacks/__init__.py
ZenPacks.oie.KannelMonitor.egg-info/PKG-INFO
ZenPacks.oie.KannelMonitor.egg-info/SOURCES.txt
ZenPacks.oie.KannelMonitor.egg-info/dependency_links.txt
ZenPacks.oie.KannelMonitor.egg-info/entry_points.txt
ZenPacks.oie.KannelMonitor.egg-info/namespace_packages.txt
ZenPacks.oie.KannelMonitor.egg-info/not-zip-safe
ZenPacks.oie.KannelMonitor.egg-info/requires.txt
ZenPacks.oie.KannelMonitor.egg-info/top_level.txt
ZenPacks/oie/__init__.py
ZenPacks/oie/KannelMonitor/__init__.py
ZenPacks/oie/KannelMonitor/config.py
ZenPacks/oie/KannelMonitor/configure.zcml
ZenPacks/oie/KannelMonitor/setuphandlers.py
ZenPacks/oie/KannelMonitor/datasources/KannelDataSource.py
ZenPacks/oie/KannelMonitor/datasources/__init__.py
ZenPacks/oie/KannelMonitor/parsers/Kannel.py
ZenPacks/oie/KannelMonitor/parsers/__init__.py
ZenPacks/oie/KannelMonitor/skins/ZenPacks.oie.KannelMonitor/editKannelMonitorDataSource.pt
ZenPacks/oie/KannelMonitor/tests/framework.py
ZenPacks/oie/KannelMonitor/tests/testKannelMonitor.py
ZenPacks/oie/KannelMonitor/tests/testKannelParser.py