Metadata-Version: 1.0
Name: ZenPacks.oie.KannelMonitor
Version: 1.0.2
Summary: ZenPack to monitor Kannel SMPP Server stats
Home-page: http://linux.last-bastion.net/LBN/up2date/monitor
Author: Optus Internet Engineering
Author-email: alan.milligan@optusnet.com.au
License: ZPL/2.1
Platform: UNKNOWN
Classifier: Framework :: Zope2
Classifier: Framework :: Plone
Classifier: Programming Language :: Python
Classifier: Programming Language :: Zope
Classifier: Topic :: System :: Monitoring
Classifier: Topic :: System :: Networking :: Monitoring
Classifier: Development Status :: 5 - Production/Stable
Classifier: License :: OSI Approved :: Zope Public License
